cfnparams/__init__.py
cfnparams/arguments.py
cfnparams/exceptions.py
cfnparams/main.py
cfnparams/params.py
cfnparams/resolution.py
cfnparams/template.py
cfnparams-0.12.dist-info/top_level.txt
cfnparams-0.12.dist-info/entry_points.txt
cfnparams-0.12.dist-info/METADATA
cfnparams-0.12.dist-info/DESCRIPTION.rst
cfnparams-0.12.dist-info/metadata.json
cfnparams-0.12.dist-info/WHEEL
cfnparams-0.12.dist-info/RECORD
