Metadata-Version: 2.0
Name: cfnparams
Version: 0.12
Summary: CloudFormation stack paramater utility.
Home-page: https://github.com/expert360/cfn-params
Author: Jonathan Sokolowski
Author-email: jsok@expert360.com
License: MIT
Keywords: aws cfn cloudformation stack
Platform: UNKNOWN
Classifier: Development Status :: 5 - Production/Stable
Classifier: Intended Audience :: Developers
Classifier: Intended Audience :: System Administrators
Classifier: License :: OSI Approved :: MIT License
Classifier: Programming Language :: Python :: 2
Classifier: Programming Language :: Python :: 2.7
Requires-Dist: boto (>=2.38.0)
Requires-Dist: retrying (>=1.3.3)
